markdown_refdocs/__init__.py
markdown_refdocs/links.py
markdown_refdocs/main.py
markdown_refdocs/markdown.py
markdown_refdocs/parsers.py
markdown_refdocs/py.typed
markdown_refdocs/types.py
tests/__init__.py
tests/test_links.py
tests/test_main.py
tests/test_markdown.py
tests/test_parsers.py
markdown_refdocs-1.4.1.dist-info/LICENSE
markdown_refdocs-1.4.1.dist-info/METADATA
markdown_refdocs-1.4.1.dist-info/WHEEL
markdown_refdocs-1.4.1.dist-info/entry_points.txt
markdown_refdocs-1.4.1.dist-info/top_level.txt
markdown_refdocs-1.4.1.dist-info/RECORD
